bruker2nifti/__init__.py
bruker2nifti/_cores.py
bruker2nifti/_getters.py
bruker2nifti/_metadata.py
bruker2nifti/_utils.py
bruker2nifti/converter.py
bruker2nifti/cli/__init__.py
bruker2nifti/cli/bruker2nii.py
bruker2nifti/cli/bruker2nii_scan.py
bruker2nifti/gui/__init__.py
bruker2nifti/gui/open.py
test/__init__.py
test/test_convert_banana.py
test/test_cores.py
test/test_getters.py
test/test_metadata.py
test/test_utils.py
bruker2nifti-1.0.4.dist-info/AUTHORS
bruker2nifti-1.0.4.dist-info/LICENCE.txt
bruker2nifti-1.0.4.dist-info/METADATA
bruker2nifti-1.0.4.dist-info/WHEEL
bruker2nifti-1.0.4.dist-info/entry_points.txt
bruker2nifti-1.0.4.dist-info/top_level.txt
bruker2nifti-1.0.4.dist-info/RECORD
