Metadata-Version: 2.1
Name: bruker2nifti
Version: 1.0.4
Summary: From raw Bruker to nifti, home-made converter.
Home-page: https://github.com/SebastianoF/bruker2nifti
Author: sebastiano ferraris
Author-email: sebastiano.ferraris@gmail.com
License: UNKNOWN
Platform: UNKNOWN
Requires-Dist: setuptools (>=30.1.0)
Requires-Dist: numpy (>=1.12.1)
Requires-Dist: nibabel (>=2.1.0)
